{
  "instance": [
    "/docs/integration/aws/eventbridge",
    "/docs/integration/aws/sns",
    "/docs/integration/azure/event-grid",
    "/docs/integration/azure/service-bus",
    "/docs/integration/gcp/pubsub"
  ],
  "intersect": {
    "domains": [
      "eventing"
    ],
    "services": [
      "integration"
    ]
  },
  "symdiff": {
    "categories": [
      "event bus",
      "push notifications",
      "message queue"
    ],
    "domains": [
      "serverless"
    ],
    "providers": [
      "aws",
      "azure",
      "gcp"
    ]
  }
}
