[
  {
    "name": "Azure Data Lake Analytics",
    "providers": ["azure"],
    "services": ["analytics"],
    "domains": ["big data"],
    "categories": ["data processing"],
    "links" {
      "self": "/products/analytics/azure/data-lake-analytics"
    }
  },
  {
    "name": "Azure Databricks",
    "providers": ["azure"],
    "services": ["analytics"],
    "domains": ["big data"],
    "categories": ["data processing"],
    "links" {
      "self": "/products/analytics/azure/databricks"
    }
  },
  {
    "name": "Azure HDInsights",
    "providers": ["azure"],
    "services": ["analytics"],
    "domains": ["big data"],
    "categories": ["data processing"],
    "links" {
      "self": "/products/analytics/azure/hdinsight"
    }
  },
  {
    "name": "Google Cloud Dataproc",
    "providers": ["gcp"],
    "services": ["analytics"],
    "domains": ["big data"],
    "categories": ["data processing"],
    "links" {
      "self": "/products/analytics/gcp/dataproc"
    }
  }
]
