{
  "instance": [
    "/products/developer-tools/aws/codecommit",
    "/products/developer-tools/azure/repos",
    "/products/developer-tools/github/github",
    "/products/developer-tools/gcp/cloud-source-repos"
  ],
  "intersect": {
    "domains": [
      "developer toolchain",
      "devops"
    ],
    "services": [
      "developer tools"
    ]
  },
  "symdiff": {
    "categories": [
      "project planning"
    ],
    "domains": [
      "project management"
    ],
    "features": [
      "community"
    ],
    "providers": [
      "aws",
      "azure",
      "github",
      "gcp"
    ]
  }
}
