[
  {
    "name": "ArcGIS Online",
    "component": "ArcGIS Notebooks",
    "providers": ["esri"],
    "services": ["geospatial"],
    "domains": ["end-user computing"],
    "categories": ["notebook","geospatial analysis","remote sensing"],
    "features": ["jupyter-based"],
    "links": {
      "self": "/products/geospatial/esri/arcgis-online/components/notebooks",
      "parent": "/products/geospatial/esri/arcgis-online"
    }
  },
  {
    "name": "Microsoft Planetary Computer",
    "component": "Hub",
    "providers": ["azure"],
    "services": ["geospatial"],
    "domains": ["managed service"],
    "categories": ["notebook","geospatial analysis","remote sensing"],
    "features": ["jupyter-based"],
    "links": {
      "self": "/products/geospatial/azure/planetary-computer/components/hub",
      "parent": "/products/geospatial/azure/planetary-computer"
    }
  },
  {
    "name": "Google Cloud Vertex AI",
    "component": "Workbench",
    "providers": ["gcp"],
    "services": ["ai"],
    "domains": ["machine learning","managed service"],
    "categories": ["notebook","model training"],
    "features": ["jupyter-based"],
    "links": {
      "self": "/products/ai/gcp/vertex-ai/components/workbench",
      "parent": "/products/ai/gcp/vertex-ai"
    }
  }
]
